Workbook
Name _A65600: #REF!
Name _A66000: #REF!
Name _A67000: #REF!
Name a: #REF!
Name aaff: #REF!
Name aff: #REF!
Name afff: #REF!
Name AGOSTO: #REF!
Name AGOSTO1: #REF!
Name Aguascalientes: #REF!
Name BC: #REF!
Name BCS: #REF!
Name Campeche: #REF!
Name Categorías_de_gastos: #REF!
Name CDMX: #REF!
Name ceroo: #REF!
Name Chiapas: #REF!
Name Chihuahua: #REF!
Name CK: #REF!
Name Coahuila: #REF!
Name Colima: #REF!
Name ControlConfianza: #REF!
Name Database: #REF!
Name datosum: '[1]2015 ESTRUCTURA'!$N$56:$N$3552
Name Durango: #REF!
Name e: #REF!
Name Edos: #REF!
Name EducationLevel: #REF!
Name EnglishAbility: #REF!
Name Est: #REF!
Name Estado: #REF!
Name Estados: #REF!
Name FEB: #REF!
Name FF: #REF!
Name FFFF: #REF!
Name Gender: #REF!
Name Genero: #REF!
Name Guanajuato: #REF!
Name Guerrero: #REF!
Name Hidalgo: #REF!
Name Jalisco: #REF!
Name MAYO: #REF!
Name México: #REF!
Name Michoacán: #REF!
Name MiColumna: '[2]24 San Luis Potosi'!#REF!
Name MiFila: '[2]24 San Luis Potosi'!#REF!
Name Morelos: #REF!
Name Nayarit: #REF!
Name NL: #REF!
Name Oaxaca: #REF!
Name ParticipantAlternate: #REF!
Name PERIODO: #REF!
Name POLICÍA_PREVENTIVO_ESTATAL: #REF!
Name PP: #REF!
Name Puebla: #REF!
Name Qroo: #REF!
Name Querétaro: #REF!
Name Reintegra: #REF!
Name Reintegros: '[2]24 San Luis Potosi'!#REF!
Name Reintegros3: #REF!

Sheet RESUMEN PROG-SUBP VF FORTAMUN
B1: FONDO DE APORTACIONES PARA EL FORTALECIMIENTO DE LOS MUNICIPIOS Y DE LAS DEMARCACIONES TERRITORIALES DEL DISTRITO FEDERAL
B2: ESTRUCTURA PROGRAMÁTICA PRESUPUESTAL FORTAMUN 2026
B3: (RESUMEN)
B4: ENTIDAD FEDERATIVA: PUEBLA
B5: MUNICIPIO: CUETZALAN DEL PROGRESO
B6: (DIEZ MILLONES TRESCIENTOS SETENTA Y UN MIL DOSCIENTOS CINCUENTA Y TRES PESOS 70/100 M.N.)
B7: AÑO | C7: ENTIDAD | D7: MUNICIPIO | E7: EJE | F7: PROGRAMA | G7: SUBPROGRAMA | H7: PROGRAMAS CON PRIORIDAD NACIONAL Y SUBPROGRAMAS | I7: ORIGEN DE LOS RECURSOS
I8: APORTACIONES FEDERALES (FORTAMUN)
H9: TOTAL | I9: =+I10+I20+I24 -> 10371254 | L9: 10371254
B10: 2026 | C10: 21 | D10: 43 | E10: 1 | H10: =+'EPP FORTAMUN 26'!L10 -> Desarrollo de las y los integrantes de las Instituciones de Seguridad Pública | I10: =+'EPP FORTAMUN 26'!M10 -> 101625
B11: 2026 | C11: 21 | D11: 43 | E11: 1 | F11: 1 | H11: =+'EPP FORTAMUN 26'!L11 -> Fortalecimiento de las Instancias de Profesionalización y Formación de las y los integrantes de las Instituciones de Seguridad Pública | I11: =+'EPP FORTAMUN 26'!M11 -> 101625
B12: 2026 | C12: 21 | D12: 43 | E12: 1 | F12: 1 | G12: 1 | H12: =+'EPP FORTAMUN 26'!L12 -> Programas de Formación Inicial y Continua conforme al Programa Rector | I12: =+'EPP FORTAMUN 26'!M12 -> 101625
B13: 2026 | C13: 21 | D13: 43 | E13: 1 | F13: 1 | G13: 2 | H13: =+'EPP FORTAMUN 26'!L24 -> Equipamiento de las Instancias de Profesionalización de las Instituciones Policiales | I13: =+'EPP FORTAMUN 26'!M24 -> 0
B14: 2026 | C14: 21 | D14: 43 | E14: 1 | F14: 1 | G14: 3 | H14: =+'EPP FORTAMUN 26'!L288 -> Infraestructura de las Instancias de Profesionalización de las Instituciones Policiales | I14: =+'EPP FORTAMUN 26'!M288 -> 0
B15: 2026 | C15: 21 | D15: 43 | E15: 1 | F15: 2 | H15: =+'EPP FORTAMUN 26'!L294 -> Servicio Profesional de Carrera | I15: =+'EPP FORTAMUN 26'!M294 -> 0
B16: 2026 | C16: 21 | D16: 43 | E16: 1 | F16: 2 | G16: 6 | H16: =+'EPP FORTAMUN 26'!L295 -> Incremento del Estado de Fuerza de las Instituciones Policiales | I16: =+'EPP FORTAMUN 26'!M295 -> 0
B17: 2026 | C17: 21 | D17: 43 | E17: 1 | F17: 2 | G17: 8 | H17: =+'EPP FORTAMUN 26'!L300 -> Evaluaciones de Control de Confianza para las y los Integrantes de las Instituciones de Seguridad Pública | I17: =+'EPP FORTAMUN 26'!M300 -> 0
B18: 2026 | C18: 21 | D18: 43 | E18: 1 | F18: 2 | G18: 10 | H18: =+'EPP FORTAMUN 26'!L305 -> Mejora Salarial, Incentivos y Reconocimientos para las y los Integrantes de las Instituciones de Seguridad Pública | I18: =+'EPP FORTAMUN 26'!M305 -> 0
B19: 2026 | C19: 21 | D19: 43 | E19: 1 | F19: 2 | G19: 11 | H19: =+'EPP FORTAMUN 26'!L316 -> Seguridad Social y Prestaciones para las y los integrantes de las Instituciones de Seguridad Pública | I19: =+'EPP FORTAMUN 26'!M316 -> 0
B20: 2026 | C20: 21 | D20: 43 | E20: 2 | H20: =+'EPP FORTAMUN 26'!L325 -> Desarrollo de las Capacidades de las Instituciones de Seguridad Pública | I20: =+'EPP FORTAMUN 26'!M325 -> 1382053.7
B21: 2026 | C21: 21 | D21: 43 | E21: 2 | F21: 3 | H21: =+'EPP FORTAMUN 26'!L326 -> Fortalecimiento de las Instituciones Policiales | I21: =+'EPP FORTAMUN 26'!M326 -> 1382053.7
B22: 2026 | C22: 21 | D22: 43 | E22: 2 | F22: 3 | G22: 12 | H22: =+'EPP FORTAMUN 26'!L327 -> Equipamiento de las Instituciones Policiales | I22: =+'EPP FORTAMUN 26'!M327 -> 1382053.7
B23: 2026 | C23: 21 | D23: 43 | E23: 2 | F23: 3 | G23: 13 | H23: =+'EPP FORTAMUN 26'!L528 -> Infraestructura de las Instituciones Policiales | I23: =+'EPP FORTAMUN 26'!M528 -> 0
B24: 2026 | C24: 21 | D24: 43 | E24: 3 | H24: =+'EPP FORTAMUN 26'!L534 -> Modernización y Estandarización de la Infraestructura Tecnológica para la Seguridad Pública | I24: =+'EPP FORTAMUN 26'!M534 -> 8887575
B25: 2026 | C25: 21 | D25: 43 | E25: 3 | F25: 8 | H25: =+'EPP FORTAMUN 26'!L535 -> Fortalecimiento Tecnológico y Operativo de los Centros de Comando y Control y las Instituciones de Seguridad Pública | I25: =+'EPP FORTAMUN 26'!M535 -> 8846375
B26: 2026 | C26: 21 | D26: 43 | E26: 3 | F26: 8 | G26: 23 | H26: =+'EPP FORTAMUN 26'!L536 -> Actualización, Modernización y Mantenimiento de la Red Nacional de Radiocomunicación | I26: =+'EPP FORTAMUN 26'!M536 -> 680750
B27: 2026 | C27: 21 | D27: 43 | E27: 3 | F27: 8 | G27: 24 | H27: =+'EPP FORTAMUN 26'!L544 -> Sistemas de Identificación Vehicular y Videovigilancia Urbana para la Seguridad Pública | I27: =+'EPP FORTAMUN 26'!M544 -> 8165625
B28: 2026 | C28: 21 | D28: 43 | E28: 3 | F28: 9 | H28: =+'EPP FORTAMUN 26'!L584 -> Modernización de las Instancias Estatales del Registro Público Vehicular (REPUVE) | I28: =+'EPP FORTAMUN 26'!M584 -> 41200
B29: =+'EPP FORTAMUN 26'!B585 -> 2026 | C29: 21 | D29: 43 | E29: 3 | F29: 9 | G29: 26 | H29: =+'EPP FORTAMUN 26'!L585 -> Fortalecimiento de la Infraestructura de los Puntos de Monitoreo Vehicular (RFID+LPR) | I29: =+'EPP FORTAMUN 26'!M585 -> 41200
H42: LIC. OSCAR PAULA CRUZ
H43: PRESIDENTE MUNICIPAL CONSTITUCIONAL

Sheet EPP FORTAMUN 26
B1: FONDO DE APORTACIONES PARA EL FORTALECIMIENTO DE LOS MUNICIPIOS Y DE LAS DEMARCACIONES TERRITORIALES DEL DISTRITO FEDERAL
B2: ESTRUCTURA PROGRAMÁTICA PRESUPUESTAL FORTAMUN 2026
B3: ENTIDAD FEDERATIVA: PUEBLA
B4: MUNICIPIO: CUETZALAN DEL PROGRESO
B5: (DIEZ MILLONES TRESCIENTOS SETENTA Y UN MIL DOSCIENTOS CINCUENTA Y TRES PESOS 70/100 M.N.)
B7: AÑO | C7: ENTIDAD | D7: MUNICIPIO | E7: EJE | F7: PROGRAMA | G7: SUBPROGRAMA | H7: CAPÍTULO | I7: CONCEPTO | J7: PARTIDA GENÉRICA | K7: BIEN | L7: PROGRAMAS CON PRIORIDAD NACIONAL Y SUBPROGRAMAS | M7: ORIGEN DE LOS RECURSOS | N7: UNIDAD DE MEDIDA | O7: CANTIDAD | P7: PERSONA / CANTIDAD 2
M8: APORTACIONES FEDERALES (FORTAMUN)
L9: TOTAL | M9: =+M10+M325+M534 -> 10371254
B10: 2026 | C10: 21 | D10: 43 | E10: 1 | L10: Desarrollo de las y los integrantes de las Instituciones de Seguridad Pública | M10: =+M11+M294 -> 101625
B11: 2026 | C11: 21 | D11: 43 | E11: 1 | F11: 1 | L11: Fortalecimiento de las Instancias de Profesionalización y Formación de las y los integrantes de las Instituciones de Seguridad Pública | M11: =M12+M24+M288 -> 101625
B12: 2026 | C12: 21 | D12: 43 | E12: 1 | F12: 1 | G12: 1 | L12: Programas de Formación Inicial y Continua conforme al Programa Rector | M12: =+M13 -> 101625
B13: 2026 | C13: 21 | D13: 43 | E13: 1 | F13: 1 | G13: 1 | H13: 3000 | L13: Servicios Generales | M13: =+M14 -> 101625
B14: 2026 | C14: 21 | D14: 43 | E14: 1 | F14: 1 | G14: 1 | H14: 3000 | I14: 3300 | L14: Servicios Profesionales, Científicos, Técnicos y Otros Servicios | M14: =+M15+M19+M21 -> 101625
B15: 2026 | C15: 21 | D15: 43 | E15: 1 | F15: 1 | G15: 1 | H15: 3000 | I15: 3300 | J15: 334 | L15: Servicios de capacitación | M15: =SUM(M16:M18) -> 101625
B16: 2026 | C16: 21 | D16: 43 | E16: 1 | F16: 1 | G16: 1 | H16: 3000 | I16: 3300 | J16: 334 | K16: 460 | L16: Curso de capacitación para Policía Municipal_Formación Inicial (Aspirantes) | M16: 101625 | N16: Servicio | O16: 1
B17: 2026 | C17: 21 | D17: 43 | E17: 1 | F17: 1 | G17: 1 | H17: 3000 | I17: 3300 | J17: 334 | K17: 459 | L17: Curso de capacitación para Policía Municipal_Formación Inicial (Activos) | N17: Servicio
B18: 2026 | C18: 21 | D18: 43 | E18: 1 | F18: 1 | G18: 1 | H18: 3000 | I18: 3300 | J18: 334 | K18: 457 | L18: Curso de capacitación para Policía Municipal_Formación Continua | N18: Servicio
B19: 2026 | C19: 21 | D19: 43 | E19: 1 | F19: 1 | G19: 1 | H19: 3000 | I19: 3300 | J19: 336 | L19: Servicios de apoyo administrativo, traducción, fotocopiado e impresión | M19: =SUM(M20:M20) -> 0
B20: 2026 | C20: 21 | D20: 43 | E20: 1 | F20: 1 | G20: 1 | H20: 3000 | I20: 3300 | J20: 336 | K20: 660 | L20: Evaluación del desempeño para Policías Municipales | N20: Evaluación
B21: 2026 | C21: 21 | D21: 43 | E21: 1 | F21: 1 | G21: 1 | H21: 3000 | I21: 3300 | J21: 339 | L21: Servicios profesionales, científicos y técnicos integrales | M21: =SUM(M22:M23) -> 0
B22: 2026 | C22: 21 | D22: 43 | E22: 1 | F22: 1 | G22: 1 | H22: 3000 | I22: 3300 | J22: 339 | K22: 1404 | L22: Subcontratación de servicios con terceros_Evaluación de Competencias Básicas de la Función para Policías Municipales | N22: Evaluación
B23: 2026 | C23: 21 | D23: 43 | E23: 1 | F23: 1 | G23: 1 | H23: 3000 | I23: 3300 | J23: 339 | K23: 1400 | L23: Subcontratación de servicios con terceros_Evaluación de Aspirantes a Instructores Evaluadores de la Función Municipal | N23: Evaluación
B24: 2026 | C24: 21 | D24: 43 | E24: 1 | F24: 1 | G24: 2 | L24: Equipamiento de las Instancias de Profesionalización de las Instituciones Policiales | M24: =+M25+M133+M145 -> 0
B25: 2026 | C25: 21 | D25: 43 | E25: 1 | F25: 1 | G25: 2 | H25: 2000 | L25: Materiales y Suministros | M25: =+M26+M37+M40+M77 -> 0
B26: 2026 | C26: 21 | D26: 43 | E26: 1 | F26: 1 | G26: 2 | H26: 2000 | I26: 2100 | L26: Materiales de Administración, Emisión de Documentos y Artículos Oficiales | M26: =+M27+M29+M31+M33+M35 -> 0
B27: 2026 | C27: 21 | D27: 43 | E27: 1 | F27: 1 | G27: 2 | H27: 2000 | I27: 2100 | J27: 211 | L27: Materiales, útiles y equipos menores de oficina | M27: =SUM(M28) -> 0
B28: 2026 | C28: 21 | D28: 43 | E28: 1 | F28: 1 | G28: 2 | H28: 2000 | I28: 2100 | J28: 211 | K28: 915 | L28: Materiales y útiles de oficina | N28: Pieza/Lote
B29: 2026 | C29: 21 | D29: 43 | E29: 1 | F29: 1 | G29: 2 | H29: 2000 | I29: 2100 | J29: 212 | L29: Materiales y útiles de impresión y reproducción | M29: =SUM(M30) -> 0
B30: 2026 | C30: 21 | D30: 43 | E30: 1 | F30: 1 | G30: 2 | H30: 2000 | I30: 2100 | J30: 212 | K30: 914 | L30: Materiales y útiles de impresión y reproducción | N30: Lote
B31: 2026 | C31: 21 | D31: 43 | E31: 1 | F31: 1 | G31: 2 | H31: 2000 | I31: 2100 | J31: 214 | L31: Materiales, útiles y equipos menores de tecnologías de la información y comunicaciones | M31: =SUM(M32) -> 0
B32: 2026 | C32: 21 | D32: 43 | E32: 1 | F32: 1 | G32: 2 | H32: 2000 | I32: 2100 | J32: 214 | K32: 916 | L32: Materiales y útiles para el procesamiento en equipos y bienes informáticos | N32: Lote
B33: 2026 | C33: 21 | D33: 43 | E33: 1 | F33: 1 | G33: 2 | H33: 2000 | I33: 2100 | J33: 216 | L33: Material de limpieza | M33: =SUM(M34) -> 0
B34: 2026 | C34: 21 | D34: 43 | E34: 1 | F34: 1 | G34: 2 | H34: 2000 | I34: 2100 | J34: 216 | K34: 907 | L34: Material de limpieza | N34: Lote
B35: 2026 | C35: 21 | D35: 43 | E35: 1 | F35: 1 | G35: 2 | H35: 2000 | I35: 2100 | J35: 217 | L35: Materiales y útiles de enseñanza | M35: =SUM(M36) -> 0
B36: 2026 | C36: 21 | D36: 43 | E36: 1 | F36: 1 | G36: 2 | H36: 2000 | I36: 2100 | J36: 217 | K36: 913 | L36: Materiales y suministros para planteles educativos | N36: Lote
B37: 2026 | C37: 21 | D37: 43 | E37: 1 | F37: 1 | G37: 2 | H37: 2000 | I37: 2600 | L37: Combustibles, lubricantes y aditivos | M37: =M38 -> 0
B38: 2026 | C38: 21 | D38: 43 | E38: 1 | F38: 1 | G38: 2 | H38: 2000 | I38: 2600 | J38: 261 | L38: Combustibles, lubricantes y aditivos | M38: =M39 -> 0
B39: 2026 | C39: 21 | D39: 43 | E39: 1 | F39: 1 | G39: 2 | H39: 2000 | I39: 2600 | J39: 261 | K39: 700 | L39: Gasolina y diésel | N39: Litro
B40: 2026 | C40: 21 | D40: 43 | E40: 1 | F40: 1 | G40: 2 | H40: 2000 | I40: 2700 | L40: Vestuario, Blancos, Prendas de Protección y Artículos Deportivos | M40: =+M41+M67+M69 -> 0
B41: 2026 | C41: 21 | D41: 43 | E41: 1 | F41: 1 | G41: 2 | H41: 2000 | I41: 2700 | J41: 271 | L41: Vestuario y uniformes | M41: =SUBTOTAL(9,M42:M66) -> 0
B42: 2026 | C42: 21 | D42: 43 | E42: 1 | F42: 1 | G42: 2 | H42: 2000 | I42: 2700 | J42: 271 | K42: 154 | L42: Boina | N42: Pieza
B43: 2026 | C43: 21 | D43: 43 | E43: 1 | F43: 1 | G43: 2 | H43: 2000 | I43: 2700 | J43: 271 | K43: 160 | L43: Botas | N43: Par
B44: 2026 | C44: 21 | D44: 43 | E44: 1 | F44: 1 | G44: 2 | H44: 2000 | I44: 2700 | J44: 271 | K44: 224 | L44: Camisa | N44: Pieza
B45: 2026 | C45: 21 | D45: 43 | E45: 1 | F45: 1 | G45: 2 | H45: 2000 | I45: 2700 | J45: 271 | K45: 228 | L45: Camisola | N45: Pieza
B46: 2026 | C46: 21 | D46: 43 | E46: 1 | F46: 1 | G46: 2 | H46: 2000 | I46: 2700 | J46: 271 | K46: 319 | L46: Chamarra | N46: Pieza
B47: 2026 | C47: 21 | D47: 43 | E47: 1 | F47: 1 | G47: 2 | H47: 2000 | I47: 2700 | J47: 271 | K47: 324 | L47: Chanchomón | N47: Pieza
B48: 2026 | C48: 21 | D48: 43 | E48: 1 | F48: 1 | G48: 2 | H48: 2000 | I48: 2700 | J48: 271 | K48: 333 | L48: Cinturón táctico | N48: Pieza
B49: 2026 | C49: 21 | D49: 43 | E49: 1 | F49: 1 | G49: 2 | H49: 2000 | I49: 2700 | J49: 271 | K49: 406 | L49: Cuartelera | N49: Pieza
B50: 2026 | C50: 21 | D50: 43 | E50: 1 | F50: 1 | G50: 2 | H50: 2000 | I50: 2700 | J50: 271 | K50: 716 | L50: Gorra tipo beisbolera | N50: Pieza
B51: 2026 | C51: 21 | D51: 43 | E51: 1 | F51: 1 | G51: 2 | H51: 2000 | I51: 2700 | J51: 271 | K51: 775 | L51: Insignias y Divisas | N51: Pieza
B52: 2026 | C52: 21 | D52: 43 | E52: 1 | F52: 1 | G52: 2 | H52: 2000 | I52: 2700 | J52: 271 | K52: 789 | L52: Kepi | N52: Pieza
B53: 2026 | C53: 21 | D53: 43 | E53: 1 | F53: 1 | G53: 2 | H53: 2000 | I53: 2700 | J53: 271 | K53: 1049 | L53: Pantalón | N53: Pieza
... B66: 2026 | C66: 21 | D66: 43 | E66: 1 | F66: 1 | G66: 2 | H66: 2000 | I66: 2700 | J66: 271 | K66: 1098 | L66: Playera tipo polo | N66: Pieza
B67: 2026 | C67: 21 | D67: 43 | E67: 1 | F67: 1 | G67: 2 | H67: 2000 | I67: 2700 | J67: 272 | L67: Prendas de seguridad y protección personal | M67: =SUBTOTAL(9,M68) -> 0
B68: 2026 | C68: 21 | D68: 43 | E68: 1 | F68: 1 | G68: 2 | H68: 2000 | I68: 2700 | J68: 272 | K68: 672 | L68: Fornitura | N68: Pieza
B69: 2026 | C69: 21 | D69: 43 | E69: 1 | F69: 1 | G69: 2 | H69: 2000 | I69: 2700 | J69: 273 | L69: Artículos deportivos | M69: =SUBTOTAL(9,M70:M76) -> 0
B70: 2026 | C70: 21 | D70: 43 | E70: 1 | F70: 1 | G70: 2 | H70: 2000 | I70: 2700 | J70: 273 | K70: 379 | L70: Conos | N70: Pieza
B71: 2026 | C71: 21 | D71: 43 | E71: 1 | F71: 1 | G71: 2 | H71: 2000 | I71: 2700 | J71: 273 | K71: 405 | L71: Cronómetro | N71: Pieza
B72: 2026 | C72: 21 | D72: 43 | E72: 1 | F72: 1 | G72: 2 | H72: 2000 | I72: 2700 | J72: 273 | K72: 356 | L72: Colchoneta de entrenamiento | N72: Pieza
B73: 2026 | C73: 21 | D73: 43 | E73: 1 | F73: 1 | G73: 2 | H73: 2000 | I73: 2700 | J73: 273 | K73: 414 | L73: Cuerdas de entrenamiento | N73: Pieza
B74: 2026 | C74: 21 | D74: 43 | E74: 1 | F74: 1 | G74: 2 | H74: 2000 | I74: 2700 | J74: 273 | K74: 499 | L74: Domi (cojín para golpeo) | N74: Pieza
B75: 2026 | C75: 21 | D75: 43 | E75: 1 | F75: 1 | G75: 2 | H75: 2000 | I75: 2700 | J75: 273 | K75: 1144 | L75: Postes de entrenamiento | N75: Pieza
B76: 2026 | C76: 21 | D76: 43 | E76: 1 | F76: 1 | G76: 2 | H76: 2000 | I76: 2700 | J76: 273 | K76: 1031 | L76: Palchagui (cojín para pateo) | N76: Pieza
B77: 2026 | C77: 21 | D77: 43 | E77: 1 | F77: 1 | G77: 2 | H77: 2000 | I77: 2800 | L77: Materiales y Suministros para Seguridad | M77: =+M78+M85 -> 0
B78: 2026 | C78: 21 | D78: 43 | E78: 1 | F78: 1 | G78: 2 | H78: 2000 | I78: 2800 | J78: 282 | L78: Materiales de Seguridad Pública | M78: =SUBTOTAL(9,M79:M84) -> 0
B79: 2026 | C79: 21 | D79: 43 | E79: 1 | F79: 1 | G79: 2 | H79: 2000 | I79: 2800 | J79: 282 | K79: 139 | L79: Bengalas | N79: Pieza
B80: 2026 | C80: 21 | D80: 43 | E80: 1 | F80: 1 | G80: 2 | H80: 2000 | I80: 2800 | J80: 282 | K80: 265 | L80: Cartucho de entrenamiento arma corta | N80: Pieza
B81: 2026 | C81: 21 | D81: 43 | E81: 1 | F81: 1 | G81: 2 | H81: 2000 | I81: 2800 | J81: 282 | K81: 266 | L81: Cartucho de entrenamiento arma larga | N81: Pieza
B82: 2026 | C82: 21 | D82: 43 | E82: 1 | F82: 1 | G82: 2 | H82: 2000 | I82: 2800 | J82: 282 | K82: 268 | L82: Cartuchos para arma corta | N82: Millar
B83: 2026 | C83: 21 | D83: 43 | E83: 1 | F83: 1 | G83: 2 | H83: 2000 | I83: 2800 | J83: 282 | K83: 272 | L83: Cartuchos para arma larga | N83: Millar
B84: 2026 | C84: 21 | D84: 43 | E84: 1 | F84: 1 | G84: 2 | H84: 2000 | I84: 2800 | J84: 282 | K84: 647 | L84: Estructura metálica para siluetas | N84: Pieza
B85: 2026 | C85: 21 | D85: 43 | E85: 1 | F85: 1 | G85: 2 | H85: 2000 | I85: 2800 | J85: 283 | L85: Prendas de protección para seguridad pública y nacional | M85: =SUBTOTAL(9,M86:M127) -> 0
B86: 2026 | C86: 21 | D86: 43 | E86: 1 | F86: 1 | G86: 2 | H86: 2000 | I86: 2800 | J86: 283 | K86: 113 | L86: Bastón policial PR-24 | N86: Pieza
B87: 2026 | C87: 21 | D87: 43 | E87: 1 | F87: 1 | G87: 2 | H87: 2000 | I87: 2800 | J87: 283 | K87: 236 | L87: Candado de mano de nylon | N87: Pieza
B88: 2026 | C88: 21 | D88: 43 | E88: 1 | F88: 1 | G88: 2 | H88: 2000 | I88: 2800 | J88: 283 | K88: 240 | L88: Candado de mano metálico (esposas) | N88: Pieza
B89: 2026 | C89: 21 | D89: 43 | E89: 1 | F89: 1 | G89: 2 | H89: 2000 | I89: 2800 | J89: 283 | K89: 247 | L89: Careta para gotcha | N89: Pieza
B90: 2026 | C90: 21 | D90: 43 | E90: 1 | F90: 1 | G90: 2 | H90: 2000 | I90: 2800 | J90: 283 | K90: 278 | L90: Casco (Especificar) | N90: Pieza
B91: 2026 | C91: 21 | D91: 43 | E91: 1 | F91: 1 | G91: 2 | H91: 2000 | I91: 2800 | J91: 283 | K91: 303 | L91: Chaleco balístico mínimo nivel III-A, con dos placas balísticas nivel IV | N91: Pieza
B92: 2026 | C92: 21 | D92: 43 | E92: 1 | F92: 1 | G92: 2 | H92: 2000 | I92: 2800 | J92: 283 | K92: 313 | L92: Chaleco táctico | N92: Pieza
B93: 2026 | C93: 21 | D93: 43 | E93: 1 | F93: 1 | G93: 2 | H93: 2000 | I93: 2800 | J93: 283 | K93: 318 | L93: Chalecos Balísticos antipunta | N93: Pieza
B94: 2026 | C94: 21 | D94: 43 | E94: 1 | F94: 1 | G94: 2 | H94: 2000 | I94: 2800 | J94: 283 | K94: 330 | L94: Cinturón | N94: Pieza
B95: 2026 | C95: 21 | D95: 43 | E95: 1 | F95: 1 | G95: 2 | H95: 2000 | I95: 2800 | J95: 283 | K95: 346 | L95: Coderas (ciclista, motociclista y tácticas) | N95: Par
B96: 2026 | C96: 21 | D96: 43 | E96: 1 | F96: 1 | G96: 2 | H96: 2000 | I96: 2800 | J96: 283 | K96: 412 | L96: Cuchillos de utilería | N96: Pieza
B97: 2026 | C97: 21 | D97: 43 | E97: 1 | F97: 1 | G97: 2 | H97: 2000 | I97: 2800 | J97: 283 | K97: 418 | L97: Cuerdas de rescate | N97: Pieza
... B127: 2026 | C127: 21 | D127: 43 | E127: 1 | F127: 1 | G127: 2 | H127: 2000 | I127: 2800 | J127: 283 | K127: 70 | L127: Arnés de rappel | N127: Pieza
B128: 2026 | C128: 21 | D128: 43 | E128: 1 | F128: 1 | G128: 2 | H128: 2000 | I128: 2900 | J128: 294 | L128: Refacciones y accesorios menores de equipo de cómputo y tecnologías de la información | M128: =SUBTOTAL(9,M129) -> 0
B129: 2026 | C129: 21 | D129: 43 | E129: 1 | F129: 1 | G129: 2 | H129: 2000 | I129: 2900 | J129: 294 | K129: 1196 | L129: Refacciones y accesorios para equipo de cómputo | N129: Pieza/Lote
B130: 2026 | C130: 21 | D130: 43 | E130: 1 | F130: 1 | G130: 2 | H130: 2000 | I130: 2900 | J130: 297 | L130: Refacciones y accesorios menores de equipo de defensa y seguridad | M130: =SUBTOTAL(9,M131:M132) -> 0
B131: 2026 | C131: 21 | D131: 43 | E131: 1 | F131: 1 | G131: 2 | H131: 2000 | I131: 2900 | J131: 297 | K131: 803 | L131: Kit de limpieza de armas | N131: Kit
B132: 2026 | C132: 21 | D132: 43 | E132: 1 | F132: 1 | G132: 2 | H132: 2000 | I132: 2900 | J132: 297 | K132: 390 | L132: Contenedores para limpieza de armas | N132: Pieza
B133: 2026 | C133: 21 | D133: 43 | E133: 1 | F133: 1 | G133: 2 | H133: 3000 | L133: Servicios Generales | M133: =+M134+M139+M142 -> 0
B134: 2026 | C134: 21 | D134: 43 | E134: 1 | F134: 1 | G134: 2 | H134: 3000 | I134: 3100 | L134: Servicios Básicos | M134: =+M135+M137 -> 0
B135: 2026 | C135: 21 | D135: 43 | E135: 1 | F135: 1 | G135: 2 | H135: 3000 | I135: 3100 | J135: 311 | L135: Energía eléctrica | M135: =+M136 -> 0
B136: 2026 | C136: 21 | D136: 43 | E136: 1 | F136: 1 | G136: 2 | H136: 3000 | I136: 3100 | J136: 311 | K136: 1264 | L136: Servicio de energía eléctrica | N136: Servicio
B137: 2026 | C137: 21 | D137: 43 | E137: 1 | F137: 1 | G137: 2 | H137: 3000 | I137: 3100 | J137: 317 | L137: Servicios de acceso de internet, redes y procesamiento de información | M137: =SUM(M138:M138) -> 0
B138: 2026 | C138: 21 | D138: 43 | E138: 1 | F138: 1 | G138: 2 | H138: 3000 | I138: 3100 | J138: 317 | K138: 1271 | L138: Servicios de conducción de señales analógicas y digitales | N138: Servicio
B139: 2026 | C139: 21 | D139: 43 | E139: 1 | F139: 1 | G139: 2 | H139: 3000 | I139: 3200 | L139: Servicios de Arrendamiento | M139: =+M140 -> 0
B140: 2026 | C140: 21 | D140: 43 | E140: 1 | F140: 1 | G140: 2 | H140: 3000 | I140: 3200 | J140: 323 | L140: Arrendamiento de Mobiliario y Equipo de Administración, Educacional y Recreativo | M140: =+M141 -> 0
B141: 2026 | C141: 21 | D141: 43 | E141: 1 | F141: 1 | G141: 2 | H141: 3000 | I141: 3200 | J141: 323 | K141: 77 | L141: Arrendamiento de Mobiliario y Equipo de Administración, Educacional y Recreativo | N141: Servicio
B142: 2026 | C142: 21 | D142: 43 | E142: 1 | F142: 1 | G142: 2 | H142: 3000 | I142: 3500 | L142: Servicios de Instalación, Reparación, Mantenimiento y Conservación | M142: =+M143 -> 0
...
